docdeid/__init__.py
docdeid/annotation.py
docdeid/deidentifier.py
docdeid/document.py
docdeid/ds/__init__.py
docdeid/ds/ds.py
docdeid/ds/lookup.py
docdeid/pattern.py
docdeid/process/__init__.py
docdeid/process/annotation_processor.py
docdeid/process/annotator.py
docdeid/process/doc_processor.py
docdeid/process/redactor.py
docdeid/py.typed
docdeid/str/__init__.py
docdeid/str/processor.py
docdeid/tokenizer.py
docdeid/utils.py
docdeid-1.0.1.dist-info/LICENSE.md
docdeid-1.0.1.dist-info/METADATA
docdeid-1.0.1.dist-info/WHEEL
docdeid-1.0.1.dist-info/RECORD
