Metadata-Version: 2.3
Name: docdeid
Version: 1.0.1
Summary: Create your own document de-identifier using docdeid, a simple framework independent of language or domain.
License: MIT
Keywords: python,document de-identification,de-identification,document de-identifier,de-identifier
Author: Vincent Menger
Author-email: vmenger@protonmail.com
Requires-Python: >=3.9,<4.0
Classifier: License :: OSI Approved :: MIT License
Classifier: Programming Language :: Python
Classifier: Programming Language :: Python :: 3
Classifier: Programming Language :: Python :: 3.9
Classifier: Programming Language :: Python :: 3.10
Classifier: Programming Language :: Python :: 3.11
Classifier: Programming Language :: Python :: 3.12
Classifier: Programming Language :: Python :: 3.13
Classifier: Topic :: Software Development :: Libraries :: Python Modules
Classifier: Topic :: Software Development :: Pre-processors
Classifier: Topic :: Text Processing
Classifier: Topic :: Text Processing :: Linguistic
Requires-Dist: frozendict (>=2.3.10,<3.0.0)
Requires-Dist: numpy (>=1.23.1,<3.0)
